cpc.geofiles-0.4.3-py3.7-nspkg.pth
cpc/geofiles/__init__.py
cpc/geofiles/conversion.py
cpc/geofiles/datasets.py
cpc/geofiles/exceptions.py
cpc/geofiles/loading.py
cpc/geofiles/reading.py
cpc/geofiles/writing.py
cpc/geofiles/data/station-list-tmean.csv
cpc.geofiles-0.4.3.dist-info/AUTHORS.md
cpc.geofiles-0.4.3.dist-info/LICENSE.md
cpc.geofiles-0.4.3.dist-info/METADATA
cpc.geofiles-0.4.3.dist-info/WHEEL
cpc.geofiles-0.4.3.dist-info/namespace_packages.txt
cpc.geofiles-0.4.3.dist-info/top_level.txt
cpc.geofiles-0.4.3.dist-info/RECORD
