Metadata-Version: 2.1
Name: cpc.geofiles
Version: 0.4.3
Summary: CPC geospatial file interaction (reading, writing, etc.)
Home-page: https://github.com/noaa-nws-cpc/cpc.geofiles
Author: Mike Charles
Author-email: mike.charles@noaa.gov
License: CC
Platform: UNKNOWN
Classifier: Development Status :: 1 - Planning
Classifier: Environment :: Console
Classifier: Intended Audience :: Science/Research
Classifier: Programming Language :: Python
Classifier: Programming Language :: Python :: 3
Classifier: Operating System :: OS Independent
Classifier: Topic :: Scientific/Engineering :: Atmospheric Science
Classifier: License :: CC0 1.0 Universal (CC0 1.0) Public Domain Dedication
Requires-Dist: cpc.geogrids
Requires-Dist: numpy
Requires-Dist: cpc.units
Requires-Dist: jinja2
Requires-Dist: xarray
